nonebot_plugin_helpwithpic/__init__.py
nonebot_plugin_helpwithpic/basedata.py
nonebot_plugin_helpwithpic/config.py
nonebot_plugin_helpwithpic/draw.py
nonebot_plugin_helpwithpic/draw_contect.py
nonebot_plugin_helpwithpic/hwp_main.py
nonebot_plugin_helpwithpic/jsondata.py
nonebot_plugin_helpwithpic/plugins_data.py
nonebot_plugin_helpwithpic/utils/fonts.py
nonebot_plugin_helpwithpic/utils/types.py
nonebot_plugin_helpwithpic-1.6.3.dist-info/licenses/LICENSE
nonebot_plugin_helpwithpic-1.6.3.dist-info/METADATA
nonebot_plugin_helpwithpic-1.6.3.dist-info/WHEEL
nonebot_plugin_helpwithpic-1.6.3.dist-info/top_level.txt
nonebot_plugin_helpwithpic-1.6.3.dist-info/RECORD
