Metadata-Version: 2.4
Name: nonebot-plugin-helpwithpic
Version: 1.6.3
Summary: nonebot插件-动态帮助图片制作
Author: cubstaryow
Author-email: cub_staryow@outlook.com
License:                     GNU GENERAL PUBLIC LICENSE
Project-URL: repository, https://github.com/cubstaryow/nonebot-plugin-HelpWithPic
Keywords: egg,bacon,sausage,tomatoes,Lobster Thermidor
Classifier: Development Status :: 4 - Beta
Classifier: Programming Language :: Python
Requires-Python: >=3.10
License-File: LICENSE
Requires-Dist: nonebot2
Requires-Dist: anyio
Requires-Dist: nonebot-adapter-onebot
Requires-Dist: nonebot-plugin-localstore
Requires-Dist: aiohttp
Requires-Dist: pil_utils
Requires-Dist: pillow
Dynamic: license-file
